urlcon/__init__.py
urlcon/__version__.py
urlcon/const.py
urlcon/constructor.py
urlcon-1.0.0.dist-info/METADATA
urlcon-1.0.0.dist-info/WHEEL
urlcon-1.0.0.dist-info/RECORD
